rclone_decrypt/__init__.py
rclone_decrypt/cli.py
rclone_decrypt/decrypt.py
rclone_decrypt/gui.py
rclone_decrypt-0.1.3.dist-info/LICENSE.md
rclone_decrypt-0.1.3.dist-info/METADATA
rclone_decrypt-0.1.3.dist-info/WHEEL
rclone_decrypt-0.1.3.dist-info/entry_points.txt
rclone_decrypt-0.1.3.dist-info/RECORD
