Metadata-Version: 2.1
Name: rclone_decrypt
Version: 0.1.3
Summary: Wrapper around rclone to decrypt files encrypted with rclone
Home-page: https://github.com/MitchellThompkins/rclone-decrypt
License: MIT
Author: Mitchell Thompkins
Author-email: mitchell.thompkins@gmail.com
Requires-Python: >=3.8.1
Classifier: License :: OSI Approved :: MIT License
Classifier: Programming Language :: Python :: 3
Classifier: Programming Language :: Python :: 3.9
Classifier: Programming Language :: Python :: 3.10
Classifier: Programming Language :: Python :: 3.11
Classifier: Programming Language :: Python :: 3.12
Classifier: Programming Language :: Python :: 3.13
Requires-Dist: click (>=8.1.3,<9.0.0)
Requires-Dist: python-rclone (>=0.0.2,<0.0.3)
Requires-Dist: python-statemachine (>=2.0.0,<3.0.0)
Requires-Dist: tkinterdnd2 (>=0.3.0,<0.4.0)
Project-URL: Repository, https://github.com/MitchellThompkins/rclone-decrypt
